feishu_sdk/__init__.py
feishu_sdk_py-0.0.1.dist-info/LICENSE
feishu_sdk_py-0.0.1.dist-info/LICENSE_996
feishu_sdk_py-0.0.1.dist-info/METADATA
feishu_sdk_py-0.0.1.dist-info/WHEEL
feishu_sdk_py-0.0.1.dist-info/top_level.txt
feishu_sdk_py-0.0.1.dist-info/RECORD
