Metadata-Version: 2.1
Name: feishu-sdk-py
Version: 0.0.1
Summary: Feishu Python SDK
Home-page: https://github.com/Thoxvi/feishu-sdk-py
Author: Thoxvi
Author-email: A@Thoxvi.com
License: UNKNOWN
Keywords: api feishu sdk python 996-icu-license pypi pypi-source
Platform: UNKNOWN
Requires-Python: >=3.4
Requires-Dist: requests
